{
  "date": "20251114",
  "foreign_ratio_ranking": [
    {
      "stock_id": "4763",
      "name": "材料*-KY",
      "foreign_ratio": 0.05336605
    },
    {
      "stock_id": "8150",
      "name": "南茂",
      "foreign_ratio": 0.03894944
    },
    {
      "stock_id": "2486",
      "name": "一詮",
      "foreign_ratio": 0.02574447
    },
    {
      "stock_id": "3624",
      "name": "光頡",
      "foreign_ratio": 0.02344452
    },
    {
      "stock_id": "8070",
      "name": "長華*",
      "foreign_ratio": 0.01852137
    },
    {
      "stock_id": "6265",
      "name": "方土昶",
      "foreign_ratio": 0.0183305
    },
    {
      "stock_id": "5340",
      "name": "建榮",
      "foreign_ratio": 0.01626003
    },
    {
      "stock_id": "6209",
      "name": "今國光",
      "foreign_ratio": 0.01527296
    },
    {
      "stock_id": "8390",
      "name": "金益鼎",
      "foreign_ratio": 0.01201671
    },
    {
      "stock_id": "4142",
      "name": "國光生",
      "foreign_ratio": 0.01146499
    },
    {
      "stock_id": "6173",
      "name": "信昌電",
      "foreign_ratio": 0.01102863
    },
    {
      "stock_id": "6155",
      "name": "鈞寶",
      "foreign_ratio": 0.01076979
    },
    {
      "stock_id": "8271",
      "name": "宇瞻",
      "foreign_ratio": 0.00965767
    },
    {
      "stock_id": "3356",
      "name": "奇偶",
      "foreign_ratio": 0.0094694
    },
    {
      "stock_id": "8299",
      "name": "群聯",
      "foreign_ratio": 0.00877183
    },
    {
      "stock_id": "4989",
      "name": "榮科",
      "foreign_ratio": 0.00807104
    },
    {
      "stock_id": "8112",
      "name": "至上",
      "foreign_ratio": 0.00788611
    },
    {
      "stock_id": "2731",
      "name": "雄獅",
      "foreign_ratio": 0.00749268
    },
    {
      "stock_id": "6435",
      "name": "大中",
      "foreign_ratio": 0.00742099
    },
    {
      "stock_id": "2337",
      "name": "旺宏",
      "foreign_ratio": 0.00732951
    },
    {
      "stock_id": "6531",
      "name": "愛普*",
      "foreign_ratio": 0.00706634
    },
    {
      "stock_id": "3709",
      "name": "鑫聯大投控",
      "foreign_ratio": 0.00689005
    },
    {
      "stock_id": "1795",
      "name": "美時",
      "foreign_ratio": 0.00670489
    },
    {
      "stock_id": "8103",
      "name": "瀚荃",
      "foreign_ratio": 0.00668451
    },
    {
      "stock_id": "2027",
      "name": "大成鋼",
      "foreign_ratio": 0.00666575
    },
    {
      "stock_id": "6625",
      "name": "必應",
      "foreign_ratio": 0.00643409
    },
    {
      "stock_id": "6589",
      "name": "台康生技",
      "foreign_ratio": 0.00626573
    },
    {
      "stock_id": "3537",
      "name": "堡達",
      "foreign_ratio": 0.00608076
    },
    {
      "stock_id": "6432",
      "name": "今展科",
      "foreign_ratio": 0.00604805
    },
    {
      "stock_id": "3609",
      "name": "三一東林",
      "foreign_ratio": 0.0059345
    },
    {
      "stock_id": "1316",
      "name": "上曜",
      "foreign_ratio": 0.00588413
    },
    {
      "stock_id": "6603",
      "name": "富強鑫",
      "foreign_ratio": 0.00578876
    },
    {
      "stock_id": "3581",
      "name": "博磊",
      "foreign_ratio": 0.00578363
    },
    {
      "stock_id": "6418",
      "name": "詠昇",
      "foreign_ratio": 0.00564857
    },
    {
      "stock_id": "4906",
      "name": "正文",
      "foreign_ratio": 0.00563385
    },
    {
      "stock_id": "6584",
      "name": "南俊國際",
      "foreign_ratio": 0.00561135
    },
    {
      "stock_id": "3167",
      "name": "大量",
      "foreign_ratio": 0.00560866
    },
    {
      "stock_id": "5328",
      "name": "華容",
      "foreign_ratio": 0.00523998
    },
    {
      "stock_id": "3006",
      "name": "晶豪科",
      "foreign_ratio": 0.00505999
    },
    {
      "stock_id": "8932",
      "name": "智通*",
      "foreign_ratio": 0.00504533
    },
    {
      "stock_id": "6163",
      "name": "華電網",
      "foreign_ratio": 0.00502246
    },
    {
      "stock_id": "3135",
      "name": "凌航",
      "foreign_ratio": 0.00496816
    },
    {
      "stock_id": "1708",
      "name": "東鹼",
      "foreign_ratio": 0.00473933
    },
    {
      "stock_id": "8096",
      "name": "擎亞",
      "foreign_ratio": 0.0046805
    },
    {
      "stock_id": "2364",
      "name": "倫飛",
      "foreign_ratio": 0.00456196
    },
    {
      "stock_id": "1802",
      "name": "台玻",
      "foreign_ratio": 0.00454375
    },
    {
      "stock_id": "1727",
      "name": "中華化",
      "foreign_ratio": 0.00453075
    },
    {
      "stock_id": "1560",
      "name": "中砂",
      "foreign_ratio": 0.00432472
    },
    {
      "stock_id": "3625",
      "name": "西勝",
      "foreign_ratio": 0.00426314
    },
    {
      "stock_id": "4967",
      "name": "十銓",
      "foreign_ratio": 0.00424632
    }
  ],
  "invest_ratio_ranking": [
    {
      "stock_id": "9802",
      "name": "鈺齊-KY",
      "invest_ratio": 0.00345288
    },
    {
      "stock_id": "6510",
      "name": "精測",
      "invest_ratio": 0.00283632
    },
    {
      "stock_id": "3694",
      "name": "海華",
      "invest_ratio": 0.00269769
    },
    {
      "stock_id": "6223",
      "name": "旺矽",
      "invest_ratio": 0.00257028
    },
    {
      "stock_id": "8021",
      "name": "尖點",
      "invest_ratio": 0.00247573
    },
    {
      "stock_id": "2481",
      "name": "強茂",
      "invest_ratio": 0.00238148
    },
    {
      "stock_id": "6442",
      "name": "光聖",
      "invest_ratio": 0.00231436
    },
    {
      "stock_id": "3653",
      "name": "健策",
      "invest_ratio": 0.00225298
    },
    {
      "stock_id": "6679",
      "name": "鈺太",
      "invest_ratio": 0.00221918
    },
    {
      "stock_id": "2402",
      "name": "毅嘉",
      "invest_ratio": 0.00175589
    },
    {
      "stock_id": "6531",
      "name": "愛普*",
      "invest_ratio": 0.0016728
    },
    {
      "stock_id": "5439",
      "name": "高技",
      "invest_ratio": 0.00163483
    },
    {
      "stock_id": "2316",
      "name": "楠梓電",
      "invest_ratio": 0.00140089
    },
    {
      "stock_id": "3596",
      "name": "智易",
      "invest_ratio": 0.00136144
    },
    {
      "stock_id": "3357",
      "name": "臺慶科",
      "invest_ratio": 0.00118587
    },
    {
      "stock_id": "5234",
      "name": "達興材料",
      "invest_ratio": 0.00111959
    },
    {
      "stock_id": "2408",
      "name": "南亞科",
      "invest_ratio": 0.00111243
    },
    {
      "stock_id": "3515",
      "name": "華擎",
      "invest_ratio": 0.00110881
    },
    {
      "stock_id": "3131",
      "name": "弘塑",
      "invest_ratio": 0.00102683
    },
    {
      "stock_id": "2368",
      "name": "金像電",
      "invest_ratio": 0.0008946
    },
    {
      "stock_id": "6449",
      "name": "鈺邦",
      "invest_ratio": 0.00080493
    },
    {
      "stock_id": "6805",
      "name": "富世達",
      "invest_ratio": 0.0007877
    },
    {
      "stock_id": "6781",
      "name": "AES-KY",
      "invest_ratio": 0.00070242
    },
    {
      "stock_id": "2449",
      "name": "京元電子",
      "invest_ratio": 0.00069843
    },
    {
      "stock_id": "6213",
      "name": "聯茂",
      "invest_ratio": 0.00065297
    },
    {
      "stock_id": "5536",
      "name": "聖暉*",
      "invest_ratio": 0.00063668
    },
    {
      "stock_id": "5274",
      "name": "信驊",
      "invest_ratio": 0.00063488
    },
    {
      "stock_id": "2383",
      "name": "台光電",
      "invest_ratio": 0.00063127
    },
    {
      "stock_id": "3030",
      "name": "德律",
      "invest_ratio": 0.00060961
    },
    {
      "stock_id": "6890",
      "name": "來億-KY",
      "invest_ratio": 0.00057739
    },
    {
      "stock_id": "4966",
      "name": "譜瑞-KY",
      "invest_ratio": 0.00056209
    },
    {
      "stock_id": "6757",
      "name": "台灣虎航",
      "invest_ratio": 0.00053315
    },
    {
      "stock_id": "2881",
      "name": "富邦金",
      "invest_ratio": 0.00052484
    },
    {
      "stock_id": "1303",
      "name": "南亞",
      "invest_ratio": 0.00042092
    },
    {
      "stock_id": "8210",
      "name": "勤誠",
      "invest_ratio": 0.00041948
    },
    {
      "stock_id": "3189",
      "name": "景碩",
      "invest_ratio": 0.00040936
    },
    {
      "stock_id": "3491",
      "name": "昇達科",
      "invest_ratio": 0.0004051
    },
    {
      "stock_id": "6196",
      "name": "帆宣",
      "invest_ratio": 0.00037615
    },
    {
      "stock_id": "3715",
      "name": "定穎投控",
      "invest_ratio": 0.00031332
    },
    {
      "stock_id": "3665",
      "name": "貿聯-KY",
      "invest_ratio": 0.00030508
    },
    {
      "stock_id": "3706",
      "name": "神達",
      "invest_ratio": 0.0002931
    },
    {
      "stock_id": "2731",
      "name": "雄獅",
      "invest_ratio": 0.00027874
    },
    {
      "stock_id": "6472",
      "name": "保瑞",
      "invest_ratio": 0.00023799
    },
    {
      "stock_id": "2455",
      "name": "全新",
      "invest_ratio": 0.00023796
    },
    {
      "stock_id": "6415",
      "name": "矽力*-KY",
      "invest_ratio": 0.00023684
    },
    {
      "stock_id": "2360",
      "name": "致茂",
      "invest_ratio": 0.00022339
    },
    {
      "stock_id": "1522",
      "name": "堤維西",
      "invest_ratio": 0.0002176
    },
    {
      "stock_id": "3526",
      "name": "凡甲",
      "invest_ratio": 0.00019942
    },
    {
      "stock_id": "3036",
      "name": "文曄",
      "invest_ratio": 0.00019324
    },
    {
      "stock_id": "3264",
      "name": "欣銓",
      "invest_ratio": 0.00019259
    }
  ],
  "foreign_ratio_5d_ranking": [
    {
      "stock_id": "3715",
      "name": "定穎投控",
      "foreign_ratio": 0.13429293
    },
    {
      "stock_id": "6919",
      "name": "康霈*",
      "foreign_ratio": 0.12119065
    },
    {
      "stock_id": "1815",
      "name": "富喬",
      "foreign_ratio": 0.10405208
    },
    {
      "stock_id": "4763",
      "name": "材料*-KY",
      "foreign_ratio": 0.09730821
    },
    {
      "stock_id": "5340",
      "name": "建榮",
      "foreign_ratio": 0.08378906
    },
    {
      "stock_id": "5351",
      "name": "鈺創",
      "foreign_ratio": 0.08266054
    },
    {
      "stock_id": "2486",
      "name": "一詮",
      "foreign_ratio": 0.07427829
    },
    {
      "stock_id": "8150",
      "name": "南茂",
      "foreign_ratio": 0.05595966
    },
    {
      "stock_id": "8070",
      "name": "長華*",
      "foreign_ratio": 0.05009285
    },
    {
      "stock_id": "3013",
      "name": "晟銘電",
      "foreign_ratio": 0.0453831
    },
    {
      "stock_id": "6265",
      "name": "方土昶",
      "foreign_ratio": 0.04312484
    },
    {
      "stock_id": "3060",
      "name": "銘異",
      "foreign_ratio": 0.04189347
    },
    {
      "stock_id": "3491",
      "name": "昇達科",
      "foreign_ratio": 0.03579476
    },
    {
      "stock_id": "8390",
      "name": "金益鼎",
      "foreign_ratio": 0.03129548
    },
    {
      "stock_id": "8110",
      "name": "華東",
      "foreign_ratio": 0.03068901
    },
    {
      "stock_id": "6485",
      "name": "點序",
      "foreign_ratio": 0.03005724
    },
    {
      "stock_id": "2439",
      "name": "美律",
      "foreign_ratio": 0.02931443
    },
    {
      "stock_id": "4739",
      "name": "康普",
      "foreign_ratio": 0.02643253
    },
    {
      "stock_id": "4916",
      "name": "事欣科",
      "foreign_ratio": 0.0250534
    },
    {
      "stock_id": "3708",
      "name": "上緯投控",
      "foreign_ratio": 0.02377979
    },
    {
      "stock_id": "2337",
      "name": "旺宏",
      "foreign_ratio": 0.02348159
    },
    {
      "stock_id": "2731",
      "name": "雄獅",
      "foreign_ratio": 0.02288756
    },
    {
      "stock_id": "4142",
      "name": "國光生",
      "foreign_ratio": 0.02266386
    },
    {
      "stock_id": "1708",
      "name": "東鹼",
      "foreign_ratio": 0.02249061
    },
    {
      "stock_id": "2421",
      "name": "建準",
      "foreign_ratio": 0.02241873
    },
    {
      "stock_id": "6770",
      "name": "力積電",
      "foreign_ratio": 0.02159484
    },
    {
      "stock_id": "4967",
      "name": "十銓",
      "foreign_ratio": 0.02132144
    },
    {
      "stock_id": "6442",
      "name": "光聖",
      "foreign_ratio": 0.02127954
    },
    {
      "stock_id": "5309",
      "name": "系統電",
      "foreign_ratio": 0.02037873
    },
    {
      "stock_id": "8936",
      "name": "國統",
      "foreign_ratio": 0.02029791
    },
    {
      "stock_id": "6591",
      "name": "動力-KY",
      "foreign_ratio": 0.01996476
    },
    {
      "stock_id": "3406",
      "name": "玉晶光",
      "foreign_ratio": 0.01983795
    },
    {
      "stock_id": "3498",
      "name": "陽程",
      "foreign_ratio": 0.0196008
    },
    {
      "stock_id": "8039",
      "name": "台虹",
      "foreign_ratio": 0.01942457
    },
    {
      "stock_id": "3624",
      "name": "光頡",
      "foreign_ratio": 0.01906412
    },
    {
      "stock_id": "3010",
      "name": "華立",
      "foreign_ratio": 0.0189677
    },
    {
      "stock_id": "9802",
      "name": "鈺齊-KY",
      "foreign_ratio": 0.01865003
    },
    {
      "stock_id": "8064",
      "name": "東捷",
      "foreign_ratio": 0.01852348
    },
    {
      "stock_id": "1809",
      "name": "中釉",
      "foreign_ratio": 0.01819304
    },
    {
      "stock_id": "8996",
      "name": "高力",
      "foreign_ratio": 0.01797536
    },
    {
      "stock_id": "1802",
      "name": "台玻",
      "foreign_ratio": 0.01769059
    },
    {
      "stock_id": "6510",
      "name": "精測",
      "foreign_ratio": 0.01746222
    },
    {
      "stock_id": "5315",
      "name": "光聯",
      "foreign_ratio": 0.01700018
    },
    {
      "stock_id": "4979",
      "name": "華星光",
      "foreign_ratio": 0.01650812
    },
    {
      "stock_id": "8155",
      "name": "博智",
      "foreign_ratio": 0.01595014
    },
    {
      "stock_id": "2451",
      "name": "創見",
      "foreign_ratio": 0.01567719
    },
    {
      "stock_id": "8054",
      "name": "安國",
      "foreign_ratio": 0.01565808
    },
    {
      "stock_id": "8096",
      "name": "擎亞",
      "foreign_ratio": 0.01553089
    },
    {
      "stock_id": "8112",
      "name": "至上",
      "foreign_ratio": 0.01489308
    },
    {
      "stock_id": "5289",
      "name": "宜鼎",
      "foreign_ratio": 0.01469082
    }
  ],
  "invest_ratio_5d_ranking": [
    {
      "stock_id": "3715",
      "name": "定穎投控",
      "invest_ratio": 0.02608449
    },
    {
      "stock_id": "3167",
      "name": "大量",
      "invest_ratio": 0.02017841
    },
    {
      "stock_id": "2481",
      "name": "強茂",
      "invest_ratio": 0.01519438
    },
    {
      "stock_id": "5289",
      "name": "宜鼎",
      "invest_ratio": 0.0144538
    },
    {
      "stock_id": "6781",
      "name": "AES-KY",
      "invest_ratio": 0.01355674
    },
    {
      "stock_id": "6274",
      "name": "台燿",
      "invest_ratio": 0.01164194
    },
    {
      "stock_id": "3653",
      "name": "健策",
      "invest_ratio": 0.01093177
    },
    {
      "stock_id": "8021",
      "name": "尖點",
      "invest_ratio": 0.01017721
    },
    {
      "stock_id": "6531",
      "name": "愛普*",
      "invest_ratio": 0.00886829
    },
    {
      "stock_id": "3260",
      "name": "威剛",
      "invest_ratio": 0.00841873
    },
    {
      "stock_id": "2368",
      "name": "金像電",
      "invest_ratio": 0.00837265
    },
    {
      "stock_id": "2337",
      "name": "旺宏",
      "invest_ratio": 0.00706047
    },
    {
      "stock_id": "6442",
      "name": "光聖",
      "invest_ratio": 0.00703201
    },
    {
      "stock_id": "8210",
      "name": "勤誠",
      "invest_ratio": 0.00643206
    },
    {
      "stock_id": "3443",
      "name": "創意",
      "invest_ratio": 0.00641691
    },
    {
      "stock_id": "9802",
      "name": "鈺齊-KY",
      "invest_ratio": 0.00457233
    },
    {
      "stock_id": "6679",
      "name": "鈺太",
      "invest_ratio": 0.00454749
    },
    {
      "stock_id": "3665",
      "name": "貿聯-KY",
      "invest_ratio": 0.00381965
    },
    {
      "stock_id": "5439",
      "name": "高技",
      "invest_ratio": 0.00347402
    },
    {
      "stock_id": "5274",
      "name": "信驊",
      "invest_ratio": 0.00326696
    },
    {
      "stock_id": "5234",
      "name": "達興材料",
      "invest_ratio": 0.00313486
    },
    {
      "stock_id": "2316",
      "name": "楠梓電",
      "invest_ratio": 0.0027197
    },
    {
      "stock_id": "3694",
      "name": "海華",
      "invest_ratio": 0.00269769
    },
    {
      "stock_id": "3491",
      "name": "昇達科",
      "invest_ratio": 0.00267064
    },
    {
      "stock_id": "2408",
      "name": "南亞科",
      "invest_ratio": 0.00248884
    },
    {
      "stock_id": "1303",
      "name": "南亞",
      "invest_ratio": 0.00242885
    },
    {
      "stock_id": "6669",
      "name": "緯穎",
      "invest_ratio": 0.00239254
    },
    {
      "stock_id": "3661",
      "name": "世芯-KY",
      "invest_ratio": 0.00225965
    },
    {
      "stock_id": "3596",
      "name": "智易",
      "invest_ratio": 0.00217831
    },
    {
      "stock_id": "3515",
      "name": "華擎",
      "invest_ratio": 0.00215286
    },
    {
      "stock_id": "6213",
      "name": "聯茂",
      "invest_ratio": 0.00213248
    },
    {
      "stock_id": "6890",
      "name": "來億-KY",
      "invest_ratio": 0.00183841
    },
    {
      "stock_id": "6805",
      "name": "富世達",
      "invest_ratio": 0.00182338
    },
    {
      "stock_id": "1319",
      "name": "東陽",
      "invest_ratio": 0.00177804
    },
    {
      "stock_id": "2731",
      "name": "雄獅",
      "invest_ratio": 0.00176891
    },
    {
      "stock_id": "2402",
      "name": "毅嘉",
      "invest_ratio": 0.00175589
    },
    {
      "stock_id": "3037",
      "name": "欣興",
      "invest_ratio": 0.00155748
    },
    {
      "stock_id": "1702",
      "name": "南僑",
      "invest_ratio": 0.00112916
    },
    {
      "stock_id": "8114",
      "name": "振樺電",
      "invest_ratio": 0.00111589
    },
    {
      "stock_id": "4967",
      "name": "十銓",
      "invest_ratio": 0.00108282
    },
    {
      "stock_id": "3529",
      "name": "力旺",
      "invest_ratio": 0.00090358
    },
    {
      "stock_id": "2383",
      "name": "台光電",
      "invest_ratio": 0.00090159
    },
    {
      "stock_id": "2204",
      "name": "中華",
      "invest_ratio": 0.00089892
    },
    {
      "stock_id": "8299",
      "name": "群聯",
      "invest_ratio": 0.00089533
    },
    {
      "stock_id": "6449",
      "name": "鈺邦",
      "invest_ratio": 0.00080493
    },
    {
      "stock_id": "6415",
      "name": "矽力*-KY",
      "invest_ratio": 0.00077228
    },
    {
      "stock_id": "2645",
      "name": "長榮航太",
      "invest_ratio": 0.00072082
    },
    {
      "stock_id": "6757",
      "name": "台灣虎航",
      "invest_ratio": 0.00068548
    },
    {
      "stock_id": "4966",
      "name": "譜瑞-KY",
      "invest_ratio": 0.00067451
    },
    {
      "stock_id": "2421",
      "name": "建準",
      "invest_ratio": 0.00065827
    }
  ],
  "foreign_ratio_10d_ranking": [
    {
      "stock_id": "3715",
      "name": "定穎投控",
      "foreign_ratio": 0.13750275
    },
    {
      "stock_id": "6919",
      "name": "康霈*",
      "foreign_ratio": 0.11773251
    },
    {
      "stock_id": "8070",
      "name": "長華*",
      "foreign_ratio": 0.11524112
    },
    {
      "stock_id": "1815",
      "name": "富喬",
      "foreign_ratio": 0.09645984
    },
    {
      "stock_id": "5351",
      "name": "鈺創",
      "foreign_ratio": 0.09259315
    },
    {
      "stock_id": "5340",
      "name": "建榮",
      "foreign_ratio": 0.07906349
    },
    {
      "stock_id": "2486",
      "name": "一詮",
      "foreign_ratio": 0.07522231
    },
    {
      "stock_id": "4763",
      "name": "材料*-KY",
      "foreign_ratio": 0.06825014
    },
    {
      "stock_id": "8110",
      "name": "華東",
      "foreign_ratio": 0.06519587
    },
    {
      "stock_id": "2439",
      "name": "美律",
      "foreign_ratio": 0.0560076
    },
    {
      "stock_id": "8150",
      "name": "南茂",
      "foreign_ratio": 0.05076808
    },
    {
      "stock_id": "6265",
      "name": "方土昶",
      "foreign_ratio": 0.04983556
    },
    {
      "stock_id": "2337",
      "name": "旺宏",
      "foreign_ratio": 0.04854327
    },
    {
      "stock_id": "3060",
      "name": "銘異",
      "foreign_ratio": 0.04853283
    },
    {
      "stock_id": "3013",
      "name": "晟銘電",
      "foreign_ratio": 0.04388817
    },
    {
      "stock_id": "2421",
      "name": "建準",
      "foreign_ratio": 0.04208403
    },
    {
      "stock_id": "2731",
      "name": "雄獅",
      "foreign_ratio": 0.03646615
    },
    {
      "stock_id": "3491",
      "name": "昇達科",
      "foreign_ratio": 0.03418976
    },
    {
      "stock_id": "3105",
      "name": "穩懋",
      "foreign_ratio": 0.02967745
    },
    {
      "stock_id": "6485",
      "name": "點序",
      "foreign_ratio": 0.02957102
    },
    {
      "stock_id": "8390",
      "name": "金益鼎",
      "foreign_ratio": 0.02925628
    },
    {
      "stock_id": "6515",
      "name": "穎崴",
      "foreign_ratio": 0.02912185
    },
    {
      "stock_id": "4739",
      "name": "康普",
      "foreign_ratio": 0.02870214
    },
    {
      "stock_id": "8936",
      "name": "國統",
      "foreign_ratio": 0.02849884
    },
    {
      "stock_id": "3406",
      "name": "玉晶光",
      "foreign_ratio": 0.0260167
    },
    {
      "stock_id": "8088",
      "name": "品安",
      "foreign_ratio": 0.02596035
    },
    {
      "stock_id": "5521",
      "name": "工信",
      "foreign_ratio": 0.0244759
    },
    {
      "stock_id": "8096",
      "name": "擎亞",
      "foreign_ratio": 0.02446106
    },
    {
      "stock_id": "2451",
      "name": "創見",
      "foreign_ratio": 0.02363796
    },
    {
      "stock_id": "6706",
      "name": "惠特",
      "foreign_ratio": 0.02293044
    },
    {
      "stock_id": "3010",
      "name": "華立",
      "foreign_ratio": 0.02282992
    },
    {
      "stock_id": "4915",
      "name": "致伸",
      "foreign_ratio": 0.02262548
    },
    {
      "stock_id": "6770",
      "name": "力積電",
      "foreign_ratio": 0.02242332
    },
    {
      "stock_id": "3624",
      "name": "光頡",
      "foreign_ratio": 0.02070038
    },
    {
      "stock_id": "6603",
      "name": "富強鑫",
      "foreign_ratio": 0.02040718
    },
    {
      "stock_id": "3498",
      "name": "陽程",
      "foreign_ratio": 0.02007409
    },
    {
      "stock_id": "3430",
      "name": "奇鈦科",
      "foreign_ratio": 0.01999046
    },
    {
      "stock_id": "1809",
      "name": "中釉",
      "foreign_ratio": 0.01985729
    },
    {
      "stock_id": "6510",
      "name": "精測",
      "foreign_ratio": 0.0193821
    },
    {
      "stock_id": "2745",
      "name": "五福",
      "foreign_ratio": 0.01922592
    },
    {
      "stock_id": "2753",
      "name": "八方雲集",
      "foreign_ratio": 0.01905145
    },
    {
      "stock_id": "1708",
      "name": "東鹼",
      "foreign_ratio": 0.01887216
    },
    {
      "stock_id": "8054",
      "name": "安國",
      "foreign_ratio": 0.01877844
    },
    {
      "stock_id": "4916",
      "name": "事欣科",
      "foreign_ratio": 0.01855977
    },
    {
      "stock_id": "6548",
      "name": "長科*",
      "foreign_ratio": 0.01844985
    },
    {
      "stock_id": "8064",
      "name": "東捷",
      "foreign_ratio": 0.01839607
    },
    {
      "stock_id": "3037",
      "name": "欣興",
      "foreign_ratio": 0.01818289
    },
    {
      "stock_id": "4909",
      "name": "新復興",
      "foreign_ratio": 0.01776109
    },
    {
      "stock_id": "3363",
      "name": "上詮",
      "foreign_ratio": 0.01770598
    },
    {
      "stock_id": "8277",
      "name": "商丞",
      "foreign_ratio": 0.01744103
    }
  ],
  "invest_ratio_10d_ranking": [
    {
      "stock_id": "3167",
      "name": "大量",
      "invest_ratio": 0.03914588
    },
    {
      "stock_id": "8021",
      "name": "尖點",
      "invest_ratio": 0.02792226
    },
    {
      "stock_id": "3715",
      "name": "定穎投控",
      "invest_ratio": 0.02608449
    },
    {
      "stock_id": "6781",
      "name": "AES-KY",
      "invest_ratio": 0.02478912
    },
    {
      "stock_id": "2368",
      "name": "金像電",
      "invest_ratio": 0.02370066
    },
    {
      "stock_id": "6274",
      "name": "台燿",
      "invest_ratio": 0.0229089
    },
    {
      "stock_id": "3443",
      "name": "創意",
      "invest_ratio": 0.01381175
    },
    {
      "stock_id": "5289",
      "name": "宜鼎",
      "invest_ratio": 0.01374037
    },
    {
      "stock_id": "6531",
      "name": "愛普*",
      "invest_ratio": 0.01259518
    },
    {
      "stock_id": "2481",
      "name": "強茂",
      "invest_ratio": 0.01240726
    },
    {
      "stock_id": "3653",
      "name": "健策",
      "invest_ratio": 0.01110474
    },
    {
      "stock_id": "8299",
      "name": "群聯",
      "invest_ratio": 0.01096658
    },
    {
      "stock_id": "6805",
      "name": "富世達",
      "invest_ratio": 0.01061938
    },
    {
      "stock_id": "2337",
      "name": "旺宏",
      "invest_ratio": 0.01014481
    },
    {
      "stock_id": "6442",
      "name": "光聖",
      "invest_ratio": 0.01005102
    },
    {
      "stock_id": "3694",
      "name": "海華",
      "invest_ratio": 0.00977752
    },
    {
      "stock_id": "6679",
      "name": "鈺太",
      "invest_ratio": 0.00918594
    },
    {
      "stock_id": "5439",
      "name": "高技",
      "invest_ratio": 0.00911313
    },
    {
      "stock_id": "3661",
      "name": "世芯-KY",
      "invest_ratio": 0.00873876
    },
    {
      "stock_id": "8210",
      "name": "勤誠",
      "invest_ratio": 0.00857882
    },
    {
      "stock_id": "5234",
      "name": "達興材料",
      "invest_ratio": 0.00734063
    },
    {
      "stock_id": "8163",
      "name": "達方",
      "invest_ratio": 0.00700972
    },
    {
      "stock_id": "2383",
      "name": "台光電",
      "invest_ratio": 0.00692457
    },
    {
      "stock_id": "8358",
      "name": "金居",
      "invest_ratio": 0.00675547
    },
    {
      "stock_id": "4906",
      "name": "正文",
      "invest_ratio": 0.00659331
    },
    {
      "stock_id": "3260",
      "name": "威剛",
      "invest_ratio": 0.00653712
    },
    {
      "stock_id": "3515",
      "name": "華擎",
      "invest_ratio": 0.00577874
    },
    {
      "stock_id": "2402",
      "name": "毅嘉",
      "invest_ratio": 0.00569038
    },
    {
      "stock_id": "3015",
      "name": "全漢",
      "invest_ratio": 0.00539892
    },
    {
      "stock_id": "1319",
      "name": "東陽",
      "invest_ratio": 0.0050572
    },
    {
      "stock_id": "8436",
      "name": "大江",
      "invest_ratio": 0.00505068
    },
    {
      "stock_id": "2316",
      "name": "楠梓電",
      "invest_ratio": 0.00495238
    },
    {
      "stock_id": "3030",
      "name": "德律",
      "invest_ratio": 0.00493193
    },
    {
      "stock_id": "1702",
      "name": "南僑",
      "invest_ratio": 0.00471258
    },
    {
      "stock_id": "9802",
      "name": "鈺齊-KY",
      "invest_ratio": 0.00457233
    },
    {
      "stock_id": "6213",
      "name": "聯茂",
      "invest_ratio": 0.0045515
    },
    {
      "stock_id": "6584",
      "name": "南俊國際",
      "invest_ratio": 0.00429193
    },
    {
      "stock_id": "6669",
      "name": "緯穎",
      "invest_ratio": 0.00396111
    },
    {
      "stock_id": "6206",
      "name": "飛捷",
      "invest_ratio": 0.00388544
    },
    {
      "stock_id": "2408",
      "name": "南亞科",
      "invest_ratio": 0.0037543
    },
    {
      "stock_id": "3491",
      "name": "昇達科",
      "invest_ratio": 0.00364663
    },
    {
      "stock_id": "8112",
      "name": "至上",
      "invest_ratio": 0.00342558
    },
    {
      "stock_id": "5274",
      "name": "信驊",
      "invest_ratio": 0.00331021
    },
    {
      "stock_id": "1519",
      "name": "華城",
      "invest_ratio": 0.00309383
    },
    {
      "stock_id": "1303",
      "name": "南亞",
      "invest_ratio": 0.0029628
    },
    {
      "stock_id": "3529",
      "name": "力旺",
      "invest_ratio": 0.00289075
    },
    {
      "stock_id": "9907",
      "name": "統一實",
      "invest_ratio": 0.002723
    },
    {
      "stock_id": "3665",
      "name": "貿聯-KY",
      "invest_ratio": 0.00251133
    },
    {
      "stock_id": "2449",
      "name": "京元電子",
      "invest_ratio": 0.00239635
    },
    {
      "stock_id": "6890",
      "name": "來億-KY",
      "invest_ratio": 0.00234964
    }
  ]
}